setup.py
scipioo/Binomialdistribution.py
scipioo/Gaussiandistribution.py
scipioo/Generaldistribution.py
scipioo/__init__.py
scipioo.egg-info/PKG-INFO
scipioo.egg-info/SOURCES.txt
scipioo.egg-info/dependency_links.txt
scipioo.egg-info/not-zip-safe
scipioo.egg-info/top_level.txt